afterglowpy/__init__.py
afterglowpy/cocoon.py
afterglowpy/flux.py
afterglowpy/jet.cpython-312-x86_64-linux-gnu.so
afterglowpy/shock.cpython-312-x86_64-linux-gnu.so
afterglowpy/version.py
afterglowpy-0.8.1.dist-info/LICENSE.txt
afterglowpy-0.8.1.dist-info/METADATA
afterglowpy-0.8.1.dist-info/WHEEL
afterglowpy-0.8.1.dist-info/top_level.txt
afterglowpy-0.8.1.dist-info/RECORD
