Metadata-Version: 2.1
Name: afterglowpy
Version: 0.8.1
Summary: GRB Afterglow Models
Home-page: https://github.com/geoffryan/afterglowpy
Author: Geoffrey Ryan
Author-email: gryan@perimeterinstitute.ca
License: MIT
Project-URL: Source Code, https://github.com/geoffryan/afterglowpy
Project-URL: Documentation, https://afterglowpy.readthedocs.io
Classifier: Programming Language :: Python :: 3
Classifier: Programming Language :: C
Classifier: License :: OSI Approved :: MIT License
Classifier: Operating System :: OS Independent
Classifier: Development Status :: 4 - Beta
Classifier: Intended Audience :: Science/Research
Classifier: Topic :: Scientific/Engineering :: Astronomy
License-File: LICENSE.txt
Requires-Dist: numpy>=1.13
Requires-Dist: scipy>=0.14
Provides-Extra: docs
Requires-Dist: numpydoc; extra == "docs"
